{
    "EURUSD": 1,
    "EURGBP": 2,
    "GBPJPY": 3,
    "EURJPY": 4,
    "GBPUSD": 5,
    "USDJPY": 6,
    "AUDCAD": 7,
    "NZDUSD": 8,
    "EURJPY-OTC": 79,
    "NZDUSD-OTC": 80,
    "GBPUSD-OTC": 81,
    "AUDCAD-OTC": 86,
    "AUDUSD": 99,
    "USDCAD": 100,
    "AUDJPY": 101,
    "GBPCAD": 102,
    "GBPCHF": 103,
    "GBPAUD": 104,
    "EURCAD": 105,
    "CHFJPY": 106,
    "CADCHF": 107,
    "EURAUD": 108,
    "USDCHF": 72,
    "EURCHF": 946,
    "CADJPY": 945,
    "GBPNZD": 947,
    "NZDUSD-op": 1896,
    "EURJPY-op": 1864,
    "GBPJPY-op": 1866,
    "EURUSD-op": 1861,
    "GBPUSD-op": 1867,
    "AUDCAD-op": 1868,
    "AUDJPY-op": 1869,
    "AUDUSD-op": 1870,
    "USDZAR-OTC": 1380,
    "USDSGD-OTC": 1381,
    "USDHKD-OTC": 1382,
    "AUDUSD-OTC": 2111,
    "USDCAD-OTC": 2112,
    "AUDJPY-OTC": 2113,
    "GBPCAD-OTC": 2114,
    "GBPCHF-OTC": 2115,
    "GBPAUD-OTC": 2116,
    "EURCAD-OTC": 2117,
    "CHFJPY-OTC": 2118,
    "CADCHF-OTC": 2119,
    "EURAUD-OTC": 2120,
    "EURNZD-OTC": 2122,
    "AUDCHF-OTC": 2129,
    "AUDNZD-OTC": 2130,
    "EURCHF-OTC": 2131,
    "GBPNZD-OTC": 2132,
    "CADJPY-OTC": 2136,
    "NZDCAD-OTC": 2137,
    "NZDJPY-OTC": 2138,
    "NZDCHF-OTC": 2202
  }
  